{
    "version": 4,
    "home-page": "/Airbus A321/A32NX_MAIN.tml",
    "sub-folder": "/Airbus A321",
    "pages":
    [
        {
            "name": "/Airbus A321/A32NX_MAIN.tml",
            "states":
            [
                {
                    "name": "Pause",
                    "formula": "{$sim/time/paused$}",
                    "dataref-rounding": 0,
                    "type": "int"
                },
                {
                    "name": "CSTR",
                    "formula": "{$AirbusFBW/OHPLightsATA31[16]$} 2 round 0 eq not",
                    "dataref-rounding": 2,
                    "type": "int"
                },
                {
                    "name": "WPT",
                    "formula": "{$AirbusFBW/OHPLightsATA31[17]$} 2 round 0 eq not",
                    "dataref-rounding": 2,
                    "type": "int"
                },
                {
                    "name": "VOR.D",
                    "formula": "{$AirbusFBW/OHPLightsATA31[18]$} 2 round 0 eq not",
                    "dataref-rounding": 2,
                    "type": "int"
                },
                {
                    "name": "NDB",
                    "formula": "{$AirbusFBW/OHPLightsATA31[19]$} 2 round 0 eq not",
                    "dataref-rounding": 2,
                    "type": "int"
                },
                {
                    "name": "ARPT",
                    "formula": "{$AirbusFBW/OHPLightsATA31[20]$} 2 round 0 eq not",
                    "dataref-rounding": 2,
                    "type": "int"
                },
                {
                    "name": "Air speed",
                    "formula": "{$sim/cockpit2/gauges/indicators/airspeed_kts_pilot$}",
                    "dataref-rounding": 0,
                    "type": "int"
                },
                {
                    "name": "Master Warn",
                    "formula": "{$AirbusFBW/MasterWarn$}",
                    "dataref-rounding": 0,
                    "type": "int"
                },
                {
                    "name": "Master Caut",
                    "formula": "{$AirbusFBW/MasterCaut$}",
                    "dataref-rounding": 0,
                    "type": "int"
                },
                {
                    "name": "Heading",
                    "formula": "{$sim/cockpit2/gauges/indicators/compass_heading_deg_mag$}",
                    "dataref-rounding": 0,
                    "type": "int"
                },
                {
                    "name": "Altitude",
                    "formula": "{$sim/cockpit2/gauges/indicators/altitude_ft_pilot$} 0.3048 * 0 round",
                    "dataref-rounding": 0,
                    "type": "int"
                },
                {
                    "name": "Vertical speed",
                    "formula": "{$toliss_airbus/pfdoutputs/captain/vertical_speed$}",
                    "dataref-rounding": 0,
                    "type": "int"
                },
                {
                    "name": "ND Mode",
                    "formula": "{$AirbusFBW/NDmodeCapt$}",
                    "dataref-rounding": 0,
                    "type": "int"
                },
                {
                    "name": "ND Range",
                    "formula": "{$AirbusFBW/NDrangeCapt$}",
                    "dataref-rounding": 0,
                    "type": "int"
                },
                {
                    "name": "ADFVOR1",
                    "formula": "{$ckpt/fcu/adf1Left/anim$}",
                    "dataref-rounding": 0,
                    "type": "int"
                },
                {
                    "name": "ADFVOR2",
                    "formula": "{$ckpt/fcu/adf2Left/anim$}",
                    "dataref-rounding": 0,
                    "type": "int"
                },
                {
                    "name": "Baro Value HG",
                    "formula": "{$sim/cockpit2/gauges/actuators/barometer_setting_in_hg_pilot$}",
                    "dataref-rounding": 2,
                    "type": "float5.2"
                },
                {
                    "name": "Baro Value hPa",
                    "formula": "{$sim/cockpit2/gauges/actuators/barometer_setting_in_hg_pilot$} 33.8639 * 0 round",
                    "type": "int"
                },
                {
                    "name": "Baro Std",
                    "formula": "{$AirbusFBW/BaroStdCapt$}",
                    "type": "int"
                },
                {
                    "name": "Baro Unit",
                    "formula": "{$AirbusFBW/BaroUnitCapt$}",
                    "dataref-rounding": 0,
                    "type": "int"
                },
                {
                    "name": "LS Captain",
                    "formula": "{$AirbusFBW/OHPLightsATA31[28]$} 0 round",
                    "dataref-rounding": 3,
                    "type": "int"
                },
                {
                    "name": "FD Captain",
                    "formula": "{$AirbusFBW/OHPLightsATA31[26]$} 0 round",
                    "dataref-rounding": 3,
                    "type": "int"
                },
                {
                    "formula": "{$sim/cockpit2/autopilot/airspeed_dial_kts_mach$} 0 round",
                    "type": "int",
                    "name": "FCU speed (kn)"
                },
                {
                    "formula": "{$AirbusFBW/MachCapt$} 2 round",
                    "type": "float",
                    "dataref-rounding": 2,
                    "name": "FCU speed (mach)"
                },
                {
                    "formula": "{$sim/cockpit2/autopilot/altitude_dial_ft$}",
                    "type": "int05",
                    "name": "FCU altitude",
                    "dataref-rounding": 0
                },
                {
                    "formula": "{$sim/cockpit/autopilot/heading_mag$}",
                    "type": "int03",
                    "name": "FCU heading",
                    "dataref-rounding": 0
                },
                {
                    "formula": "{$sim/cockpit/autopilot/vertical_velocity$}",
                    "type": "float",
                    "name": "FCU vertspeed"
                },
                {
                    "formula": "{$AirbusFBW/SPDmanaged$}",
                    "type": "int",
                    "name": "FCU speed_managed",
                    "dataref-rounding": 0
                },
                {
                    "formula": "{$AirbusFBW/HDGmanaged$}",
                    "type": "int",
                    "name": "FCU lnav_managed",
                    "dataref-rounding": 0
                },
                {
                    "formula": "{$AirbusFBW/ALTmanaged$}",
                    "type": "int",
                    "name": "FCU vnav_managed",
                    "dataref-rounding": 0
                },
                {
                    "formula": "{$sim/cockpit/autopilot/airspeed_is_mach$}",
                    "type": "int",
                    "name": "FCU speed is mach",
                    "dataref-rounding": 0
                },
                {
                    "formula": "{$AirbusFBW/HDGTRKmode$}",
                    "type": "int",
                    "name": "FCU track",
                    "dataref-rounding": 0
                },
                {
                    "formula": "{$AirbusFBW/VSdashed$}",
                    "type": "int",
                    "name": "FCU vsdashed",
                    "dataref-rounding": 0
                },
                {
                    "formula": "{$AirbusFBW/SPDdashed$}",
                    "type": "int",
                    "name": "FCU spddashed",
                    "dataref-rounding": 0
                },
                {
                    "formula": "{$AirbusFBW/HDGdashed$}",
                    "type": "int",
                    "name": "FCU hdgdashed",
                    "dataref-rounding": 0
                },
                {
                    "formula": "{$AirbusFBW/ALT100_1000$}",
                    "type": "int",
                    "name": "FCU alt 100/1000",
                    "dataref-rounding": 0
                },
                {
                    "formula": "{$AirbusFBW/MetricAlt$}",
                    "type": "int",
                    "name": "FCU alt metric",
                    "dataref-rounding": 0
                },
                {
                    "formula": "{$AirbusFBW/AP1Engage$}",
                    "type": "int",
                    "name": "FCU AP 1",
                    "dataref-rounding": 0
                },
                {
                    "formula": "{$AirbusFBW/AP2Engage$}",
                    "type": "int",
                    "name": "FCU AP 2",
                    "dataref-rounding": 0
                },
                {
                    "formula": "{$AirbusFBW/ATHRmode$}",
                    "type": "int",
                    "name": "FCU A/THR",
                    "dataref-rounding": 0
                },
                {
                    "formula": "{$AirbusFBW/EXPEDilluminated$}",
                    "type": "int",
                    "name": "FCU EXPED",
                    "dataref-rounding": 0
                },
                {
                    "formula": "{$AirbusFBW/LOCilluminated$}",
                    "type": "int",
                    "name": "FCU LOC",
                    "dataref-rounding": 0
                },
                {
                    "formula": "{$AirbusFBW/APPRilluminated$}",
                    "type": "int",
                    "name": "FCU APPR",
                    "dataref-rounding": 0
                },
                {
                    "formula": "{$AirbusFBW/ParkBrake$}",
                    "type": "int",
                    "name": "Parking Brake",
                    "dataref-rounding": 0
                },
                {
                    "formula": "{$AirbusFBW/BrakeFan$}",
                    "type": "int",
                    "name": "Brake Fan",
                    "dataref-rounding": 0
                },
                {
                    "formula": "{$AirbusFBW/BrakeTemperatureArray[0]$} {$AirbusFBW/BrakeTemperatureArray[1]$} {$AirbusFBW/BrakeTemperatureArray[2]$} + + 3 / 0 round",
                    "type": "int",
                    "name": "Brake Temperature (Avg)",
                    "dataref-rounding": 0
                },
                {
                    "formula": "{$ckpt/speedbrakeUp/anim$}",
                    "type": "int",
                    "name": "Speed brake armed",
                    "dataref-rounding": 0
                },
                {
                    "formula": "{$ckpt/speedbrake/anim$} 0.24 + 0.25 / floor",
                    "type": "int",
                    "name": "Speed brake position",
                    "dataref-rounding": 2
                },
                {
                    "formula": "{$AirbusFBW/FlapLeverRatio$} 4 * 0 round",
                    "type": "int",
                    "name": "Flaps position",
                    "dataref-rounding": 2
                },
                {
                    "formula": "{$AirbusFBW/GearLever$}",
                    "type": "int",
                    "name": "Gear down"
                },
                {
                    "formula": "{$AirbusFBW/NWSnAntiSkid$}",
                    "type": "int",
                    "name": "Anti-Skid"
                },
                {
                    "formula": "{$AirbusFBW/NoseGearInd$}",
                    "type": "int",
                    "name": "Gear Nose"
                },
                {
                    "formula": "{$AirbusFBW/LeftGearInd$}",
                    "type": "int",
                    "name": "Gear Left"
                },
                {
                    "formula": "{$AirbusFBW/RightGearInd$}",
                    "type": "int",
                    "name": "Gear Right"
                },
                {
                    "formula": "{$AirbusFBW/AutoBrkLo$}",
                    "type": "int",
                    "name": "Auto Brake Low"
                },
                {
                    "formula": "{$AirbusFBW/AutoBrkMed$}",
                    "type": "int",
                    "name": "Auto Brake Medium"
                },
                {
                    "formula": "{$AirbusFBW/AutoBrkMax$}",
                    "type": "int",
                    "name": "Auto Brake Max"
                },
                {
                    "formula": "{$AirbusFBW/FMAAPFDboxing$}",
                    "type": "int",
                    "name": "FMAAPFDboxing",
                    "dataref-rounding": 0
                },
                {
                    "formula": "{$AirbusFBW/FMAAPLeftArmedBox$}",
                    "type": "int",
                    "name": "FMAAPLeftArmedBox",
                    "dataref-rounding": 0
                },
                {
                    "formula": "{$AirbusFBW/FMAAPLeftModeBox$}",
                    "type": "int",
                    "name": "FMAAPLeftModeBox",
                    "dataref-rounding": 0
                },
                {
                    "formula": "{$AirbusFBW/FMAAPFDboxing$}",
                    "type": "int",
                    "name": "FMAAPFDboxing",
                    "dataref-rounding": 0
                },
                {
                    "formula": "{$AirbusFBW/FMAAPRightArmedBox$}",
                    "type": "int",
                    "name": "FMAAPRightArmedBox",
                    "dataref-rounding": 0
                },
                {
                    "formula": "{$AirbusFBW/FMAAPRightModeBox$}",
                    "type": "int",
                    "name": "FMAAPRightModeBox",
                    "dataref-rounding": 0
                },
                {
                    "formula": "{$AirbusFBW/FMAATHRboxing$}",
                    "type": "int",
                    "name": "FMAATHRboxing",
                    "dataref-rounding": 0
                },
                {
                    "formula": "{$AirbusFBW/FMATHRWarning$}",
                    "type": "int",
                    "name": "FMATHRWarning",
                    "dataref-rounding": 0
                },
                {
                    "formula": "{$AirbusFBW/throttle_input[0]$}",
                    "type": "float",
                    "name": "Engine 1 Throttle",
                    "dataref-rounding": 1
                },
                {
                    "formula": "{$AirbusFBW/throttle_input[1]$}",
                    "type": "float",
                    "name": "Engine 2 Throttle",
                    "dataref-rounding": 1
                },
                {
                    "formula": "",
                    "name": "FMA1"
                },
                {
                    "formula": "",
                    "name": "FMA2"
                },
                {
                    "formula": "",
                    "name": "FMA3"
                },
                {
                    "formula": "",
                    "name": "FMA4"
                },
                {
                    "formula": "",
                    "name": "FMA5"
                }
            ]
        },
        {
            "name": "/Airbus A321/A32NX_OVHD_UP.tml",
            "states":
            [
                {
                    "name": "Pause",
                    "formula": "{$sim/time/paused$}",
                    "dataref-rounding": 0,
                    "type": "int"
                },
                {
                    "formula": "{$AirbusFBW/BatVolts[0]$}",
                    "type": "float",
                    "name": "Battery 1",
                    "dataref-rounding": 1
                },
                {
                    "formula": "{$AirbusFBW/BatVolts[1]$}",
                    "type": "float",
                    "name": "Battery 2",
                    "dataref-rounding": 1
                },
                {
                    "formula": "{$AirbusFBW/FireAgentSwitchAnim[10]$} ceil",
                    "type": "int",
                    "name": "Engine 1 Fire Alert",
                    "dataref-rounding": 1
                },
                {
                    "formula": "{$AirbusFBW/OHPGuardsAllATA[17]$} ceil",
                    "type": "int",
                    "name": "Engine 1 Fire Guard",
                    "dataref-rounding": 1
                },
                {
                    "formula": "{$AirbusFBW/ENGFireSwitchArray[0]$} ceil",
                    "type": "int",
                    "name": "Engine 1 Fire",
                    "dataref-rounding": 1
                }
            ]
        },
        {
            "name": "/Airbus A321/A32NX_OVHD_DOWN.tml",
            "states":
            [
                {
                    "name": "Pause",
                    "formula": "{$sim/time/paused$}",
                    "dataref-rounding": 0,
                    "type": "int"
                }
            ]
        },
        {
            "name": "/Airbus A321/A32NX_PEDESTAL.tml",
            "states":
            [
                {
                    "name": "Pause",
                    "formula": "{$sim/time/paused$}",
                    "dataref-rounding": 0,
                    "type": "int"
                },
                {
                    "formula": "{$AirbusFBW/ENGN2Speed[0]$}",
                    "type": "float",
                    "name": "Engine N2 1",
                    "dataref-rounding": 1
                },
                {
                    "formula": "{$AirbusFBW/ENGN2Speed[1]$}",
                    "type": "float",
                    "name": "Engine N2 2",
                    "dataref-rounding": 1
                },
                {
                    "formula": "{$AirbusFBW/ENGEGTArray[0]$}",
                    "type": "int",
                    "name": "Engine EGT 1",
                    "dataref-rounding": 1
                },
                {
                    "formula": "{$AirbusFBW/ENGEGTArray[1]$}",
                    "type": "int",
                    "name": "Engine EGT 2",
                    "dataref-rounding": 1
                },
                {
                    "formula": "{$AirbusFBW/fmod/eng/N1Array[0]$}",
                    "type": "float",
                    "name": "Engine N1 1",
                    "dataref-rounding": 1
                },
                {
                    "formula": "{$AirbusFBW/fmod/eng/N1Array[1]$}",
                    "type": "float",
                    "name": "Engine N1 2",
                    "dataref-rounding": 1
                },
                {
                    "formula": "{$AirbusFBW/ENGFuelFlowArray[0]$} 3600 * 0 round",
                    "type": "int",
                    "name": "Engine FF 1",
                    "dataref-rounding": 3
                },
                {
                    "formula": "{$AirbusFBW/ENGFuelFlowArray[1]$} 3600 * 0 round",
                    "type": "int",
                    "name": "Engine FF 2",
                    "dataref-rounding": 3
                },
                {
                    "formula": "{$AirbusFBW/RMP1Freq$} 200 * floor 200 /",
                    "type": "float7.3",
                    "name": "Radio",
                    "dataref-rounding": 4
                },
                {
                    "formula": "{$AirbusFBW/RMP1StbyFreq$} 200 * floor 200 /",
                    "type": "float7.3",
                    "name": "Radio Stby",
                    "dataref-rounding": 4
                },
                {
                    "formula": "{$AirbusFBW/RMP1Available$}",
                    "type": "int",
                    "name": "RMP Available",
                    "dataref-rounding": 0
                },
                {
                    "formula": "{$AirbusFBW/RMP1SelFunc$}",
                    "type": "int",
                    "name": "RMP Selector",
                    "dataref-rounding": 0
                },
                {
                    "formula": "{$ckpt/radar/sys/anim$}",
                    "type": "int",
                    "name": "Weather Radar System",
                    "dataref-rounding": 0
                },
                {
                    "formula": "{$ckpt/fped/radar/mode/anim$}",
                    "type": "int",
                    "name": "Weather Radar Mode",
                    "dataref-rounding": 0
                },
                {
                    "formula": "{$AirbusFBW/OHPLightsATA31[30]$} ceil",
                    "type": "int",
                    "name": "ECAM ENG",
                    "dataref-rounding": 2
                },
                {
                    "formula": "{$AirbusFBW/OHPLightsATA31[31]$} ceil",
                    "type": "int",
                    "name": "ECAM BLEED",
                    "dataref-rounding": 2
                },
                {
                    "formula": "{$AirbusFBW/OHPLightsATA31[32]$} ceil",
                    "type": "int",
                    "name": "ECAM PRESS",
                    "dataref-rounding": 2
                },
                {
                    "formula": "{$AirbusFBW/OHPLightsATA31[33]$} ceil",
                    "type": "int",
                    "name": "ECAM ELEC",
                    "dataref-rounding": 2
                },
                {
                    "formula": "{$AirbusFBW/OHPLightsATA31[34]$} ceil",
                    "type": "int",
                    "name": "ECAM HYD",
                    "dataref-rounding": 2
                },
                {
                    "formula": "{$AirbusFBW/OHPLightsATA31[35]$} ceil",
                    "type": "int",
                    "name": "ECAM FUEL",
                    "dataref-rounding": 2
                },
                {
                    "formula": "{$AirbusFBW/OHPLightsATA31[36]$} ceil",
                    "type": "int",
                    "name": "ECAM APU",
                    "dataref-rounding": 2
                },
                {
                    "formula": "{$AirbusFBW/OHPLightsATA31[37]$} ceil",
                    "type": "int",
                    "name": "ECAM COND",
                    "dataref-rounding": 2
                },
                {
                    "formula": "{$AirbusFBW/OHPLightsATA31[38]$} ceil",
                    "type": "int",
                    "name": "ECAM DOOR",
                    "dataref-rounding": 2
                },
                {
                    "formula": "{$AirbusFBW/OHPLightsATA31[39]$} ceil",
                    "type": "int",
                    "name": "ECAM WHEEL",
                    "dataref-rounding": 2
                },
                {
                    "formula": "{$AirbusFBW/OHPLightsATA31[40]$} ceil",
                    "type": "int",
                    "name": "ECAM F/CTL",
                    "dataref-rounding": 2
                },
                {
                    "formula": "{$AirbusFBW/OHPLightsATA31[41]$} ceil",
                    "type": "int",
                    "name": "ECAM STS",
                    "dataref-rounding": 2
                },
                {
                    "formula": "{$AirbusFBW/ENG1MasterSwitch$}",
                    "type": "int",
                    "name": "Engine Master 1",
                    "dataref-rounding": 0
                },
                {
                    "formula": "{$AirbusFBW/ENG12MasterSwitch$}",
                    "type": "int",
                    "name": "Engine Master 2",
                    "dataref-rounding": 0
                },
                {
                    "formula": "{$AirbusFBW/anim/ENGModeSwitch$}",
                    "type": "int",
                    "name": "Engine Mode",
                    "dataref-rounding": 0
                },
                {
                    "formula": "{$sim/cockpit/radios/transponder_code$}",
                    "type": "int04",
                    "name": "Transponder Code",
                    "dataref-rounding": 0
                },
                {
                    "formula": "{$AirbusFBW/XPDRTCASMode$}",
                    "type": "int",
                    "name": "XPDR TCAS Mode",
                    "dataref-rounding": 0
                },
                {
                    "formula": "{$AirbusFBW/XPDRSystem$}",
                    "type": "int",
                    "name": "XPDR System",
                    "dataref-rounding": 0
                },
                {
                    "formula": "{$AirbusFBW/XPDRTCASAltSelect$}",
                    "type": "int",
                    "name": "XPDR TCAS Alt Select",
                    "dataref-rounding": 0
                },
                {
                    "formula": "{$AirbusFBW/XPDRPower$}",
                    "type": "int",
                    "name": "XPDR Power",
                    "dataref-rounding": 0
                }
            ]
        }
    ],
    "long-press-commands":
    [
        "AirbusFBW/FireTestAPU",
        "AirbusFBW/FireTestENG1",
        "AirbusFBW/FireTestENG2"
    ],
    "toliss-airbus-fma-datarefs":
    [
        "AirbusFBW/FMA1w",
        "AirbusFBW/FMA1g",
        "AirbusFBW/FMA1b",
        "AirbusFBW/FMA2w",
        "AirbusFBW/FMA2b",
        "AirbusFBW/FMA2m",
        "AirbusFBW/FMA3w",
        "AirbusFBW/FMA3b",
        "AirbusFBW/FMA3a"
    ],
    "toliss-airbus-fma-boxes":
    [
        "AirbusFBW/FMAAPFDboxing",
        "AirbusFBW/FMAAPLeftArmedBox",
        "AirbusFBW/FMAAPLeftModeBox",
        "AirbusFBW/FMAAPRightArmedBox",
        "AirbusFBW/FMAAPRightModeBox",
        "AirbusFBW/FMAATHRModeBox",
        "AirbusFBW/FMAATHRboxing",
        "AirbusFBW/FMATHRWarning"
    ]
}